{
  "$schema": "https://mintlify.com/docs.json",
  "theme": "mint",
  "name": "Kundera",
  "colors": {
    "primary": "#EC796B",
    "light": "#F8AFA6",
    "dark": "#EC796B"
  },
  "navigation": {
    "anchors": [
      {
        "anchor": "Documentation",
        "icon": "book-open",
        "groups": [
          {
            "group": "Overview",
            "icon": "house",
            "pages": [
              "index",
              "overview/why-kundera",
              "overview/architecture"
            ]
          },
          {
            "group": "Getting Started",
            "icon": "rocket",
            "pages": [
              "getting-started/quickstart",
              "getting-started/branded-types",
              "getting-started/runtime-implementations",
              "getting-started/agentic-coding"
            ]
          },
          {
            "group": "Primitives",
            "icon": "cube",
            "pages": [
              "primitives/index",
              "primitives/felt252",
              "primitives/contract-address",
              "primitives/class-hash",
              "primitives/storage-key",
              "primitives/eth-address",
              "primitives/short-strings"
            ]
          },
          {
            "group": "Core Concepts",
            "icon": "book",
            "pages": [
              "concepts/branded-types",
              "concepts/event-filtering",
              "concepts/security"
            ]
          },
          {
            "group": "Guides",
            "icon": "compass",
            "pages": [
              {
                "group": "Transport",
                "pages": [
                  "guides/provider/transport",
                  "guides/provider/providers"
                ]
              },
              {
                "group": "ABI",
                "pages": [
                  "guides/abi/encode-decode",
                  "guides/abi/events"
                ]
              },
              "guides/serialization"
            ]
          },
          {
            "group": "Skills",
            "icon": "puzzle-piece",
            "pages": [
              "skills/index",
              "skills/http-transport",
              "skills/http-provider",
              "skills/websocket-provider",
              "skills/contract-read",
              "skills/contract-write",
              "skills/contract-multicall",
              "skills/event-filtering",
              "skills/account-invoke",
              "skills/account-declare",
              "skills/account-deploy",
              "skills/wallet-modal",
              "skills/contract-viem"
            ]
          },
          {
            "group": "API Reference",
            "icon": "code",
            "pages": [
              "api/primitives",
              "api/crypto",
              "api/serde",
              "api/transport",
              "api/provider",
              "api/utils",
              "api/jsonrpc",
              "api/abi"
            ]
          }
        ]
      }
    ]
  },
  "topbarLinks": [
    {
      "name": "GitHub",
      "url": "https://github.com/starknet/kundera"
    }
  ]
}
